pretalx_orcid/__init__.py
pretalx_orcid/forms.py
pretalx_orcid/models.py
pretalx_orcid/orcid.py
pretalx_orcid/signals.py
pretalx_orcid/urls.py
pretalx_orcid/views.py
pretalx_orcid/locale/django.pot
pretalx_orcid/locale/cs/LC_MESSAGES/django.mo
pretalx_orcid/locale/cs/LC_MESSAGES/django.po
pretalx_orcid/locale/de_DE/LC_MESSAGES/.gitkeep
pretalx_orcid/locale/de_DE/LC_MESSAGES/django.mo
pretalx_orcid/locale/de_DE/LC_MESSAGES/django.po
pretalx_orcid/locale/de_DE/de/LC_MESSAGES/django.mo
pretalx_orcid/locale/de_Formal/LC_MESSAGES/django.mo
pretalx_orcid/locale/de_Formal/LC_MESSAGES/django.po
pretalx_orcid/locale/en_MOZILLA/LC_MESSAGES/django.mo
pretalx_orcid/locale/en_MOZILLA/LC_MESSAGES/django.po
pretalx_orcid/locale/es_MX/LC_MESSAGES/django.mo
pretalx_orcid/locale/es_MX/LC_MESSAGES/django.po
pretalx_orcid/locale/fr_FR/LC_MESSAGES/.gitkeep
pretalx_orcid/locale/fr_FR/LC_MESSAGES/django.mo
pretalx_orcid/locale/fr_FR/LC_MESSAGES/django.po
pretalx_orcid/locale/ja_JP/LC_MESSAGES/django.mo
pretalx_orcid/locale/ja_JP/LC_MESSAGES/django.po
pretalx_orcid/locale/zh_Hant/LC_MESSAGES/django.mo
pretalx_orcid/locale/zh_Hant/LC_MESSAGES/django.po
pretalx_orcid/locale/zh_TW/LC_MESSAGES/django.mo
pretalx_orcid/locale/zh_TW/LC_MESSAGES/django.po
pretalx_orcid/migrations/0001_initial.py
pretalx_orcid/migrations/0002_orcidprofile_data.py
pretalx_orcid/migrations/__init__.py
pretalx_orcid/static/pretalx_orcid/.gitkeep
pretalx_orcid/static/pretalx_orcid/orcid.css
pretalx_orcid/static/pretalx_orcid/orcid_16x16.png
pretalx_orcid/static/pretalx_orcid/orcid_24x24.png
pretalx_orcid/templates/pretalx_orcid/.gitkeep
pretalx_orcid/templates/pretalx_orcid/settings.html
pretalx_orcid/templates/pretalx_orcid/submission_step.html
pretalx_orcid-0.0.8.dist-info/LICENSE
pretalx_orcid-0.0.8.dist-info/METADATA
pretalx_orcid-0.0.8.dist-info/WHEEL
pretalx_orcid-0.0.8.dist-info/entry_points.txt
pretalx_orcid-0.0.8.dist-info/top_level.txt
pretalx_orcid-0.0.8.dist-info/RECORD
