Metadata-Version: 2.1
Name: pretalx-orcid
Version: 0.0.8
Summary: Gather speaker data from ORCID
Home-page: https://pretalx.com/pretalx/pretalx-orcid
Author: Tobias Kunze
Author-email: r@rixx.de
License: Apache Software License
Platform: UNKNOWN
